spacing/__init__.py
spacing/__main__.py
spacing/analyzer.py
spacing/classifier.py
spacing/cli.py
spacing/config.py
spacing/parser.py
spacing/pathfilter.py
spacing/processor.py
spacing/rules.py
spacing/types.py
spacing-0.9.0.dist-info/METADATA
spacing-0.9.0.dist-info/WHEEL
spacing-0.9.0.dist-info/entry_points.txt
spacing-0.9.0.dist-info/licenses/AUTHORS
spacing-0.9.0.dist-info/licenses/LICENSE
spacing-0.9.0.dist-info/RECORD
