Metadata-Version: 2.4
Name: spacing
Version: 0.9.0
Summary: Python blank line formatter enforcing spacing rules for clean, readable code
Project-URL: Repository, https://gitlab.com/oldmission/spacing
Project-URL: Issues, https://gitlab.com/oldmission/spacing/-/issues
Author: Greg Smethells
License: GPL-3.0-or-later
License-File: AUTHORS
License-File: LICENSE
Keywords: blank-lines,code-quality,formatter,python
Classifier: Development Status :: 5 - Production/Stable
Classifier: Intended Audience :: Developers
Classifier: Programming Language :: Python :: 3
Classifier: Programming Language :: Python :: 3.11
Classifier: Programming Language :: Python :: 3.12
Classifier: Programming Language :: Python :: 3.13
Classifier: Programming Language :: Python :: 3.14
Requires-Python: >=3.11
